blogger2hugo/__init__.py
blogger2hugo/cli.py
blogger2hugo-0.1.0.dist-info/METADATA
blogger2hugo-0.1.0.dist-info/WHEEL
blogger2hugo-0.1.0.dist-info/entry_points.txt
blogger2hugo-0.1.0.dist-info/licenses/LICENSE
blogger2hugo-0.1.0.dist-info/RECORD
