Metadata-Version: 2.4
Name: blogger2hugo
Version: 0.1.0
Summary: Convert a Blogger Atom export to Hugo Markdown with configurable slugs and link sanitization.
Project-URL: Homepage, https://github.com/yourname/blogger2hugo
Project-URL: Issues, https://github.com/yourname/blogger2hugo/issues
Author-email: Hamed Faramarzi <hamed.faramarzi@gmail.com>
License: 
License-File: LICENSE
Keywords: blogger,converter,hugo,markdown,static-site
Classifier: Development Status :: 3 - Alpha
Classifier: Environment :: Console
Classifier: Intended Audience :: Developers
Classifier: License :: OSI Approved :: MIT License
Classifier: Programming Language :: Python :: 3
Classifier: Programming Language :: Python :: 3 :: Only
Classifier: Programming Language :: Python :: 3.8
Classifier: Programming Language :: Python :: 3.9
Classifier: Programming Language :: Python :: 3.10
Classifier: Programming Language :: Python :: 3.11
Classifier: Programming Language :: Python :: 3.12
Classifier: Topic :: Internet :: WWW/HTTP
Classifier: Topic :: Text Processing :: Markup :: Markdown
Classifier: Topic :: Utilities
Requires-Python: >=3.8
Requires-Dist: beautifulsoup4>=4.12.0
Requires-Dist: html2text>=2020.1.16
Requires-Dist: python-slugify>=8.0.0
